[
null,
{"id":1,"autoRemovalTiming":0,"chanceByDamage":100,"iconIndex":1,"maxTurns":1,"message1":" has fallen!","message2":" is slain!","message3":"","message4":" revives!","minTurns":1,"motion":3,"name":"Knockout","note":"State #1 will be automatically added when\nHP reaches 0.","overlay":0,"priority":100,"releaseByDamage":false,"removeAtBattleEnd":false,"removeByDamage":false,"removeByRestriction":false,"removeByWalking":false,"restriction":4,"stepsToRemove":100,"traits":[{"code":23,"dataId":9,"value":0}]},
{"id":2,"autoRemovalTiming":1,"chanceByDamage":100,"description":"","iconIndex":0,"maxTurns":1,"message1":"","message2":"","message3":"","message4":"","minTurns":1,"motion":0,"name":"Guard","note":"","overlay":0,"priority":0,"removeAtBattleEnd":true,"removeByDamage":false,"removeByRestriction":true,"removeByWalking":false,"restriction":0,"stepsToRemove":100,"traits":[{"code":62,"dataId":1,"value":0},{"code":21,"dataId":3,"value":2},{"code":21,"dataId":6,"value":0.85}]},
{"id":3,"autoRemovalTiming":0,"chanceByDamage":100,"description":"","iconIndex":0,"maxTurns":1,"message1":"","message2":"","message3":"","message4":"","minTurns":1,"motion":0,"name":"Immortal","note":"","overlay":0,"priority":0,"removeAtBattleEnd":true,"removeByDamage":false,"removeByRestriction":true,"removeByWalking":false,"restriction":0,"stepsToRemove":100,"traits":[{"code":14,"dataId":1,"value":0}]},
{"id":4,"autoRemovalTiming":0,"chanceByDamage":100,"iconIndex":2,"maxTurns":1,"message1":" is poisoned!","message2":" is poisoned!","message3":"","message4":" is no longer poisoned!","minTurns":1,"motion":0,"overlay":1,"name":"Poison","note":"","priority":50,"releaseByDamage":false,"removeAtBattleEnd":false,"removeByDamage":false,"removeByRestriction":false,"removeByWalking":false,"restriction":0,"stepsToRemove":100,"traits":[{"code":22,"dataId":7,"value":-0.15}]},
{"id":5,"autoRemovalTiming":1,"chanceByDamage":100,"iconIndex":3,"maxTurns":3,"message1":" is blinded!","message2":" is blinded!","message3":"","message4":" is no longer blinded!","minTurns":3,"motion":0,"name":"Blind","note":"","overlay":0,"priority":60,"releaseByDamage":false,"removeAtBattleEnd":true,"removeByDamage":false,"removeByRestriction":false,"removeByWalking":false,"restriction":0,"stepsToRemove":100,"traits":[{"code":22,"dataId":0,"value":-0.5}]},
{"id":6,"autoRemovalTiming":0,"chanceByDamage":100,"iconIndex":4,"maxTurns":3,"message1":" is silenced!","message2":" is silenced!","message3":"","message4":" is no longer silenced!","minTurns":3,"motion":0,"name":"Silence","note":"","overlay":3,"priority":65,"releaseByDamage":false,"removeAtBattleEnd":true,"removeByDamage":false,"removeByRestriction":false,"removeByWalking":false,"restriction":0,"stepsToRemove":100,"traits":[{"code":42,"dataId":3,"value":0},{"code":42,"dataId":5,"value":1},{"code":42,"dataId":4,"value":0},{"code":42,"dataId":6,"value":1},{"code":42,"dataId":7,"value":1}]},
{"id":7,"autoRemovalTiming":2,"chanceByDamage":100,"iconIndex":0,"maxTurns":2,"message1":" is enraged!","message2":" is enraged!","message3":"","message4":" is no longer enraged!","minTurns":2,"motion":0,"name":"Downpour","note":"","overlay":0,"priority":70,"releaseByDamage":false,"removeAtBattleEnd":true,"removeByDamage":true,"removeByRestriction":false,"removeByWalking":false,"restriction":0,"stepsToRemove":100,"traits":[{"code":22,"dataId":7,"value":-0.3}]},
{"id":8,"autoRemovalTiming":1,"chanceByDamage":50,"iconIndex":6,"maxTurns":3,"message1":" is confused!","message2":" is confused!","message3":"","message4":" is no longer confused!","minTurns":3,"motion":0,"name":"Confusion","note":"","overlay":5,"priority":75,"releaseByDamage":false,"removeAtBattleEnd":true,"removeByDamage":true,"removeByRestriction":false,"removeByWalking":false,"restriction":2,"stepsToRemove":100,"traits":[]},
{"id":9,"autoRemovalTiming":1,"chanceByDamage":25,"iconIndex":75,"maxTurns":3,"message1":"","message2":"","message3":"","message4":"","minTurns":3,"motion":0,"name":"Draw","note":"","overlay":0,"priority":80,"releaseByDamage":false,"removeAtBattleEnd":true,"removeByDamage":true,"removeByRestriction":false,"removeByWalking":false,"restriction":4,"stepsToRemove":100,"traits":[{"code":22,"dataId":7,"value":0.1}]},
{"id":10,"autoRemovalTiming":1,"chanceByDamage":100,"iconIndex":8,"maxTurns":3,"message1":" falls asleep!","message2":" falls asleep!","message3":" is sleeping.","message4":" wakes up!","minTurns":3,"motion":2,"name":"Sleep","note":"<Category: Bypass Death Removal>","overlay":7,"priority":90,"releaseByDamage":true,"removeAtBattleEnd":true,"removeByDamage":true,"removeByRestriction":false,"removeByWalking":false,"restriction":4,"stepsToRemove":100,"traits":[{"code":22,"dataId":1,"value":-1}]},
{"id":11,"autoRemovalTiming":1,"chanceByDamage":100,"iconIndex":74,"maxTurns":3,"message1":" is slowed!","message2":" is slowed!","message3":" moves more slowly.","message4":" is no longer affected by slow.","minTurns":3,"motion":0,"name":"Slowed","note":"","overlay":2,"priority":90,"releaseByDamage":true,"removeAtBattleEnd":true,"removeByDamage":false,"removeByRestriction":false,"removeByWalking":false,"restriction":0,"stepsToRemove":100,"traits":[{"code":21,"dataId":6,"value":0.5}]},
{"id":12,"autoRemovalTiming":1,"chanceByDamage":100,"traits":[{"code":21,"dataId":6,"value":5}],"iconIndex":46,"maxTurns":3,"message1":" is moving more quickly!","message2":" is moving more quickly!","message3":" is affected by haste.","message4":" is no longer affected by haste.","minTurns":3,"motion":0,"name":"Hasten","note":"","overlay":0,"priority":60,"removeAtBattleEnd":true,"removeByDamage":false,"removeByRestriction":false,"removeByWalking":false,"restriction":0,"stepsToRemove":100},
{"id":13,"autoRemovalTiming":1,"chanceByDamage":100,"traits":[{"code":21,"dataId":3,"value":8},{"code":14,"dataId":13,"value":1}],"iconIndex":43,"maxTurns":1,"message1":"ha","message2":"hu","message3":"he","message4":"ho","minTurns":1,"motion":0,"name":"Protected","note":"<Custom Decay Effect>\nuser.addState(74);\n</Custom Decay Effect>","overlay":0,"priority":60,"removeAtBattleEnd":true,"removeByDamage":false,"removeByRestriction":false,"removeByWalking":false,"restriction":0,"stepsToRemove":100},
{"id":14,"autoRemovalTiming":1,"chanceByDamage":100,"traits":[{"code":21,"dataId":5,"value":8},{"code":14,"dataId":14,"value":1}],"iconIndex":45,"maxTurns":1,"message1":" is protected by barrier!","message2":" is protected by barrier!","message3":" is inside a barrier.","message4":" is no longer protected by barrier.","minTurns":1,"motion":0,"name":"HUHAHU!","note":"<Custom Decay Effect>\nuser.addState(75);\n</Custom Decay Effect>","overlay":0,"priority":50,"removeAtBattleEnd":true,"removeByDamage":false,"removeByRestriction":false,"removeByWalking":false,"restriction":0,"stepsToRemove":100},
{"id":15,"autoRemovalTiming":1,"chanceByDamage":100,"traits":[],"iconIndex":16,"maxTurns":3,"message1":" is stopped!","message2":" is stopped!","message3":"'s time flow is stopped.","message4":"'s time flow is start to move again.","minTurns":3,"motion":0,"name":"Stopped","note":"","overlay":0,"priority":50,"removeAtBattleEnd":false,"removeByDamage":false,"removeByRestriction":false,"removeByWalking":false,"restriction":4,"stepsToRemove":100},
{"id":16,"autoRemovalTiming":1,"chanceByDamage":100,"traits":[],"iconIndex":25,"maxTurns":2,"message1":" is paralyzed!","message2":" is paralyzed!","message3":" is paralyzed.","message4":" is no longer paralyzed.","minTurns":2,"motion":0,"name":"Paralyzed","note":"","overlay":8,"priority":50,"removeAtBattleEnd":true,"removeByDamage":false,"removeByRestriction":false,"removeByWalking":false,"restriction":4,"stepsToRemove":100},
{"id":17,"autoRemovalTiming":1,"chanceByDamage":100,"traits":[],"iconIndex":0,"maxTurns":2,"message1":" is concentrating.","message2":"","message3":" is concentrating.","message4":"","minTurns":2,"motion":0,"name":"Concentrated","note":"","overlay":0,"priority":50,"removeAtBattleEnd":true,"removeByDamage":false,"removeByRestriction":false,"removeByWalking":false,"restriction":0,"stepsToRemove":100},
{"id":18,"autoRemovalTiming":1,"chanceByDamage":100,"traits":[{"code":22,"dataId":0,"value":2}],"iconIndex":0,"maxTurns":2,"message1":"","message2":"","message3":"","message4":"","minTurns":2,"motion":0,"name":"Focused","note":"","overlay":0,"priority":50,"removeAtBattleEnd":true,"removeByDamage":false,"removeByRestriction":false,"removeByWalking":false,"restriction":0,"stepsToRemove":100},
{"id":19,"autoRemovalTiming":1,"chanceByDamage":100,"traits":[{"code":22,"dataId":1,"value":1}],"iconIndex":0,"maxTurns":3,"message1":"","message2":"","message3":"","message4":"","minTurns":3,"motion":0,"name":"Optical Camouflage","note":"","overlay":0,"priority":50,"removeAtBattleEnd":true,"removeByDamage":false,"removeByRestriction":false,"removeByWalking":false,"restriction":0,"stepsToRemove":100},
{"id":20,"autoRemovalTiming":1,"chanceByDamage":100,"traits":[],"iconIndex":6,"maxTurns":1,"message1":" is distracted!","message2":" is distracted!","message3":" is distracted!","message4":" is no longer distracted!","minTurns":1,"motion":0,"name":"Distracted","note":"","overlay":0,"priority":50,"removeAtBattleEnd":false,"removeByDamage":false,"removeByRestriction":false,"removeByWalking":false,"restriction":4,"stepsToRemove":100},
{"id":21,"autoRemovalTiming":0,"chanceByDamage":100,"traits":[{"code":44,"dataId":112,"value":1}],"iconIndex":0,"maxTurns":1,"message1":"The party cannot escape!","message2":"","message3":"","message4":"","minTurns":1,"motion":0,"name":"Bound","note":"","overlay":0,"priority":50,"removeAtBattleEnd":true,"removeByDamage":false,"removeByRestriction":false,"removeByWalking":false,"restriction":0,"stepsToRemove":100},
{"id":22,"autoRemovalTiming":0,"chanceByDamage":100,"traits":[{"code":22,"dataId":7,"value":-0.05},{"code":21,"dataId":2,"value":0.5},{"code":11,"dataId":5,"value":0.6}],"iconIndex":64,"maxTurns":3,"message1":" is Burned!","message2":" is Burned!","message3":"","message4":"","minTurns":3,"motion":0,"name":"Burn","note":"","overlay":0,"priority":50,"removeAtBattleEnd":true,"removeByDamage":false,"removeByRestriction":false,"removeByWalking":false,"restriction":0,"stepsToRemove":100},
{"id":23,"autoRemovalTiming":0,"chanceByDamage":100,"traits":[{"code":21,"dataId":3,"value":0.7},{"code":11,"dataId":2,"value":0.6},{"code":11,"dataId":1,"value":1.5}],"iconIndex":0,"maxTurns":1,"message1":" is Frozen!","message2":" is Frozen!","message3":"","message4":"","minTurns":1,"motion":0,"name":"Freeze","note":"","overlay":0,"priority":50,"removeAtBattleEnd":true,"removeByDamage":true,"removeByRestriction":false,"removeByWalking":false,"restriction":4,"stepsToRemove":100},
{"id":24,"autoRemovalTiming":0,"chanceByDamage":100,"traits":[{"code":21,"dataId":6,"value":0.8},{"code":11,"dataId":3,"value":2},{"code":11,"dataId":2,"value":0.3}],"iconIndex":0,"maxTurns":1,"message1":" is Soaked!","message2":" is Soaked!","message3":"","message4":"","minTurns":1,"motion":0,"name":"Wet","note":"","overlay":0,"priority":50,"removeAtBattleEnd":true,"removeByDamage":false,"removeByRestriction":false,"removeByWalking":false,"restriction":0,"stepsToRemove":100},
{"id":25,"autoRemovalTiming":2,"chanceByDamage":100,"traits":[{"code":11,"dataId":8,"value":0.1},{"code":21,"dataId":2,"value":2},{"code":21,"dataId":4,"value":2}],"iconIndex":6,"maxTurns":5,"message1":" is Messed Up!","message2":" is Messed Up!","message3":"","message4":"","minTurns":5,"motion":0,"name":"Chaotic","note":"","overlay":0,"priority":50,"removeAtBattleEnd":true,"removeByDamage":true,"removeByRestriction":false,"removeByWalking":false,"restriction":2,"stepsToRemove":100},
{"id":26,"autoRemovalTiming":0,"chanceByDamage":100,"traits":[{"code":22,"dataId":0,"value":-0.5}],"iconIndex":0,"maxTurns":1,"message1":" is Trembling!","message2":" is Trembling!","message3":"","message4":"","minTurns":1,"motion":0,"name":"Tremor","note":"","overlay":0,"priority":50,"removeAtBattleEnd":true,"removeByDamage":false,"removeByRestriction":false,"removeByWalking":false,"restriction":0,"stepsToRemove":100},
{"id":27,"autoRemovalTiming":0,"chanceByDamage":100,"traits":[{"code":23,"dataId":4,"value":1.3}],"iconIndex":0,"maxTurns":1,"message1":"","message2":"","message3":"","message4":"","minTurns":1,"motion":0,"name":"Dualcast","note":"<Custom Action Start Effect>\n// If a chained action is stored...\nif ($gameTemp._chainAction === undefined) {\n  // ...then set the action to the user's current action.\n  $gameTemp._chainAction = user.currentAction();\n} else {\n  // ...then clear the stored action.\n  $gameTemp._chainAction = undefined;\n}\n</Custom Action Start Effect>\n\n<Custom Action End Effect>\n// If a chained action is stored...\nif ($gameTemp._chainAction) {\n  // Set the 'action' variable to the chained action.\n  var action = $gameTemp._chainAction;\n  // Check if the action exists, is a skill, and is a magical attack.\n  if (action && action.isSkill() && action.isMagical()) {\n    // Get the skill used for that action.\n    var skill = action.item();\n    // Check if the user can pay the skill cost.\n    if (user.canPaySkillCost(skill)) {\n      // Check if the battle system is DTB.\n      if (BattleManager.isDTB()) {\n        // If it is, add the action to queue.\n        user.setAction(0, action);\n      // If the battle system isn't DTB...\n      } else {\n        // ...make it a forced forced.\n        BattleManager.queueForceAction(user, skill.id, -2);\n      }\n    }\n  }\n}\n</Custom Action End Effect>\n\n<Custom Remove Effect>\n// Clear the chained action effect.\n$gameTemp._chainAction = undefined;\n</Custom Remove Effect>\n","overlay":0,"priority":50,"removeAtBattleEnd":true,"removeByDamage":false,"removeByRestriction":false,"removeByWalking":false,"restriction":0,"stepsToRemove":100},
{"id":28,"autoRemovalTiming":2,"chanceByDamage":100,"traits":[{"code":21,"dataId":2,"value":0.5},{"code":21,"dataId":4,"value":0.5},{"code":22,"dataId":8,"value":-0.19},{"code":31,"dataId":12,"value":1},{"code":22,"dataId":9,"value":0.13}],"iconIndex":0,"maxTurns":4,"message1":"","message2":"","message3":"","message4":"","minTurns":4,"motion":0,"name":"HakkeroBlade","note":"<Custom Apply Effect>\n// Check if user is an actor.\nif (user.isActor()) {\n  // Archive the previous settings.\n  user._prevCharName = user._prevCharName || user._characterName;\n  user._prevCharIndex = user._prevCharIndex || user._characterIndex;\n  user._prevFaceName = user._prevFaceName || user._faceName;\n  user._prevFaceIndex = user._prevFaceIndex || user._faceIndex;\n  user._prevBattlerName = user._prevBattlerName || user._battlerName;\n  // Check if the actor ID is 1.\n  if (user.actorId() === 1) {\n    // The filename of the character graphic without the file extension.\n    var charName = 'maris';\n    // The index of the character graphic used.\n    var charIndex = 0;\n    // The filename of the face graphic without the file extension.\n    var faceName = 'thfs';\n    // The index of of the face graphic used.\n    var faceIndex = 0;\n    // The filename of the battler graphic without the file extension.\n    var battlerName = 'maris-furnace';\n  } \n  // Changes the character image to the setting applied from above.\n  user.setCharacterImage(charName, charIndex);\n  // Changes the face image to the setting applied from above.\n  user.setFaceImage(faceName, faceIndex);\n  // Changes the battler image from the setting applied from above.\n  user.setBattlerImage(battlerName);\n  // Refreshes the user's appearance.\n  user.refresh();\n}\n</Custom Apply Effect>\n\n<Custom Remove Effect>\n// Retrieve archived settings.\nvar charName = user._prevCharName;\nvar charIndex = user._prevCharIndex;\nvar faceName = user._prevFaceName;\nvar faceIndex = user._prevFaceIndex;\nvar battlerName = user._prevBattlerName;\n// Changes the character image to the archived setting.\nuser.setCharacterImage(charName, charIndex);\n// Changes the face image to the archived setting.\nuser.setFaceImage(faceName, faceIndex);\n// Changes the battler image from the archived setting.\nuser.setBattlerImage(battlerName);\n// Clear archived data.\nuser._priorityCharacterName = undefined;\nuser._priorityCharacterIndex = undefined;\nuser._prevFaceName = undefined;\nuser._prevFaceIndex = undefined;\nuser._priorityFaceName = undefined;\nuser._priorityFaceIndex = undefined;\nuser._prevFaceName = undefined;\nuser._prevFaceIndex = undefined;\nuser._priorityBattlerName = undefined;\nuser._prevBattlerName = undefined;\n// Refreshes the user's appearance.\nuser.refresh();\n</Custom Remove Effect>","overlay":0,"priority":50,"removeAtBattleEnd":true,"removeByDamage":false,"removeByRestriction":false,"removeByWalking":false,"restriction":0,"stepsToRemove":100},
{"id":29,"autoRemovalTiming":0,"chanceByDamage":100,"traits":[{"code":22,"dataId":0,"value":2}],"iconIndex":0,"maxTurns":1,"message1":"","message2":"","message3":"","message4":"","minTurns":1,"motion":0,"name":"Focused","note":"<Restrict>\nWeapon:18,20\n</Restrict>","overlay":0,"priority":50,"removeAtBattleEnd":true,"removeByDamage":false,"removeByRestriction":false,"removeByWalking":false,"restriction":0,"stepsToRemove":100},
{"id":30,"autoRemovalTiming":2,"chanceByDamage":100,"traits":[{"code":21,"dataId":3,"value":0.7}],"iconIndex":0,"maxTurns":2,"message1":"","message2":" is Pierced!","message3":"","message4":"","minTurns":1,"motion":0,"name":"Pierced","note":"","overlay":0,"priority":50,"removeAtBattleEnd":true,"removeByDamage":false,"removeByRestriction":false,"removeByWalking":false,"restriction":0,"stepsToRemove":100},
{"id":31,"autoRemovalTiming":2,"chanceByDamage":100,"traits":[{"code":21,"dataId":6,"value":0.9}],"iconIndex":0,"maxTurns":2,"message1":"","message2":"","message3":"","message4":"","minTurns":1,"motion":0,"name":"Slugged","note":"","overlay":0,"priority":50,"removeAtBattleEnd":true,"removeByDamage":false,"removeByRestriction":false,"removeByWalking":false,"restriction":4,"stepsToRemove":100},
{"id":32,"autoRemovalTiming":2,"chanceByDamage":100,"traits":[{"code":21,"dataId":3,"value":5},{"code":21,"dataId":5,"value":5}],"iconIndex":0,"maxTurns":2,"message1":"","message2":"","message3":"","message4":"","minTurns":2,"motion":0,"name":"Force Field","note":"","overlay":0,"priority":50,"removeAtBattleEnd":true,"removeByDamage":false,"removeByRestriction":false,"removeByWalking":false,"restriction":0,"stepsToRemove":100},
{"id":33,"autoRemovalTiming":1,"chanceByDamage":50,"traits":[{"code":21,"dataId":3,"value":2},{"code":21,"dataId":6,"value":0.6},{"code":22,"dataId":9,"value":0.24},{"code":14,"dataId":40,"value":1},{"code":22,"dataId":8,"value":-0.1}],"iconIndex":81,"maxTurns":3,"message1":"","message2":"","message3":"","message4":"","minTurns":3,"motion":0,"name":"Charging","note":"","overlay":0,"priority":50,"removeAtBattleEnd":true,"removeByDamage":true,"removeByRestriction":false,"removeByWalking":false,"restriction":0,"stepsToRemove":100},
{"id":34,"autoRemovalTiming":0,"chanceByDamage":100,"traits":[{"code":22,"dataId":7,"value":-0.15}],"iconIndex":0,"maxTurns":1,"message1":"","message2":"","message3":"","message4":"","minTurns":1,"motion":0,"name":"Lifesteal","note":"<Restrict>\nArmor: 52\n</Restrict>","overlay":0,"priority":50,"removeAtBattleEnd":true,"removeByDamage":false,"removeByRestriction":false,"removeByWalking":false,"restriction":0,"stepsToRemove":100},
{"id":35,"autoRemovalTiming":0,"chanceByDamage":100,"traits":[{"code":22,"dataId":7,"value":0.02}],"iconIndex":0,"maxTurns":1,"message1":"","message2":"","message3":"","message4":"","minTurns":1,"motion":0,"name":"Surge Ring","note":"","overlay":0,"priority":50,"removeAtBattleEnd":true,"removeByDamage":false,"removeByRestriction":false,"removeByWalking":false,"restriction":0,"stepsToRemove":100},
{"id":36,"autoRemovalTiming":2,"chanceByDamage":100,"traits":[{"code":14,"dataId":40,"value":1},{"code":21,"dataId":3,"value":2},{"code":21,"dataId":6,"value":0.5}],"iconIndex":0,"maxTurns":3,"message1":"","message2":"","message3":"","message4":"","minTurns":1,"motion":0,"name":"Guard","note":"","overlay":0,"priority":50,"removeAtBattleEnd":true,"removeByDamage":false,"removeByRestriction":true,"removeByWalking":false,"restriction":0,"stepsToRemove":100},
{"id":37,"autoRemovalTiming":1,"chanceByDamage":100,"traits":[{"code":21,"dataId":2,"value":2},{"code":21,"dataId":6,"value":3}],"iconIndex":12,"maxTurns":2,"message1":"","message2":"","message3":"","message4":"","minTurns":2,"motion":0,"name":"Attacked","note":"\n<Custom Action Start Effect>\n  var action = user.currentAction();\n  var actionId = 1;\n  var stypeId = 29;\n  if (actionId = 1) {\n      user.removeState(37);\n      user.addState(38);\n    }\n</Custom Action Start Effect>\n\n<Custom Remove Effect>\n$gameTemp._chainAction = undefined;\n</Custom Remove Effect>","overlay":0,"priority":50,"removeAtBattleEnd":true,"removeByDamage":false,"removeByRestriction":false,"removeByWalking":false,"restriction":0,"stepsToRemove":100},
{"id":38,"autoRemovalTiming":1,"chanceByDamage":100,"traits":[{"code":21,"dataId":2,"value":3},{"code":21,"dataId":6,"value":3.5},{"code":14,"dataId":37,"value":1}],"iconIndex":13,"maxTurns":2,"message1":"","message2":"","message3":"","message4":"","minTurns":2,"motion":0,"name":"Attacked 2","note":"<Custom Action Start Effect>\n  var action = user.currentAction();\n  var actionId = 1;\n  if (actionId = 1) {\n      user.removeState(38);\n      user.addState(39);\n    }\n</Custom Action Start Effect>","overlay":0,"priority":50,"removeAtBattleEnd":true,"removeByDamage":false,"removeByRestriction":false,"removeByWalking":false,"restriction":0,"stepsToRemove":100},
{"id":39,"autoRemovalTiming":1,"chanceByDamage":100,"traits":[{"code":21,"dataId":2,"value":4.2},{"code":21,"dataId":6,"value":5},{"code":14,"dataId":37,"value":1}],"iconIndex":14,"maxTurns":2,"message1":"","message2":"","message3":"","message4":"","minTurns":2,"motion":0,"name":"Attacked 3","note":"<Custom Action Start Effect>\n  var action = user.currentAction();\n  var actionId = 1;\n  if (actionId = 1) {\n      user.removeState(39);\n      user.addState(41);\n    }\n</Custom Action Start Effect>","overlay":0,"priority":50,"removeAtBattleEnd":true,"removeByDamage":false,"removeByRestriction":false,"removeByWalking":false,"restriction":0,"stepsToRemove":100},
{"id":40,"autoRemovalTiming":1,"chanceByDamage":100,"traits":[{"code":21,"dataId":3,"value":2},{"code":21,"dataId":6,"value":0.9},{"code":14,"dataId":46,"value":1},{"code":14,"dataId":47,"value":1},{"code":14,"dataId":48,"value":1},{"code":14,"dataId":49,"value":1},{"code":21,"dataId":5,"value":2},{"code":22,"dataId":1,"value":-0.25}],"iconIndex":92,"maxTurns":2,"message1":"","message2":"","message3":"","message4":"","minTurns":2,"motion":0,"name":"Defended","note":"\n<Custom Respond Effect>\n  var action = user.currentAction();\n  var actionId = 1;\n  if (actionId != 7 || actionId != 4) {\n      target.removeState(40);\n      target.addState(42);\n    }\n</Custom Respond Effect>\n\n<Category: Bypass Death Removal>","overlay":0,"priority":50,"removeAtBattleEnd":true,"removeByDamage":false,"removeByRestriction":false,"removeByWalking":false,"restriction":0,"stepsToRemove":100},
{"id":41,"autoRemovalTiming":1,"chanceByDamage":100,"traits":[{"code":21,"dataId":2,"value":5},{"code":21,"dataId":6,"value":6},{"code":14,"dataId":37,"value":1}],"iconIndex":15,"maxTurns":2,"message1":"","message2":"","message3":"","message4":"","minTurns":2,"motion":0,"name":"Attack 4","note":"<Custom Action Start Effect>\n  var action = user.currentAction();\n  var actionId = 1;\n  if (actionId = 1) {\n      user.removeState(41);\n    }\n</Custom Action Start Effect>\n\n<Custom Remove Effect>\nuser.removeState(37);\n</Custom Remove Effect>","overlay":0,"priority":50,"removeAtBattleEnd":true,"removeByDamage":false,"removeByRestriction":false,"removeByWalking":false,"restriction":0,"stepsToRemove":100},
{"id":42,"autoRemovalTiming":1,"chanceByDamage":100,"traits":[{"code":21,"dataId":3,"value":2.5},{"code":21,"dataId":6,"value":0.8},{"code":14,"dataId":40,"value":1},{"code":21,"dataId":5,"value":2.5},{"code":22,"dataId":1,"value":-0.5}],"iconIndex":93,"maxTurns":2,"message1":"","message2":"","message3":"","message4":"","minTurns":2,"motion":0,"name":"Defend 2","note":"<Custom Respond Effect>\n  var action = user.currentAction();\n  var actionId = 1;\n  if (actionId != 7 || actionId != 4) {\n      target.removeState(42);\n      target.addState(43);\n    }\n</Custom Respond Effect>\n<Category: Bypass Death Removal>","overlay":0,"priority":50,"removeAtBattleEnd":true,"removeByDamage":false,"removeByRestriction":false,"removeByWalking":false,"restriction":0,"stepsToRemove":100},
{"id":43,"autoRemovalTiming":1,"chanceByDamage":100,"traits":[{"code":21,"dataId":3,"value":3},{"code":21,"dataId":6,"value":0.7},{"code":14,"dataId":40,"value":1},{"code":21,"dataId":5,"value":3},{"code":22,"dataId":1,"value":-0.75}],"iconIndex":94,"maxTurns":2,"message1":"","message2":"","message3":"","message4":"","minTurns":2,"motion":0,"name":"Defend 3","note":"<Custom Respond Effect>\n  var action = user.currentAction();\n  var actionId = 1;\n  if (actionId != 7 || actionId != 4){\n      user.removeState(43);\n      user.addState(44);\n    }\n</Custom Respond Effect>","overlay":0,"priority":50,"removeAtBattleEnd":true,"removeByDamage":false,"removeByRestriction":false,"removeByWalking":false,"restriction":0,"stepsToRemove":100},
{"id":44,"autoRemovalTiming":1,"chanceByDamage":100,"traits":[{"code":21,"dataId":3,"value":4.5},{"code":21,"dataId":6,"value":0.6},{"code":14,"dataId":40,"value":1},{"code":21,"dataId":5,"value":3.5},{"code":22,"dataId":1,"value":-1}],"iconIndex":95,"maxTurns":2,"message1":"","message2":"","message3":"","message4":"","minTurns":2,"motion":0,"name":"Defend 4","note":"<Custom Respond Effect>\n  var action = user.currentAction();\n  var actionId = 1;\n  if (actionId != 7 || actionId != 4){\n      user.removeState(40);\n    }\n</Custom Respond Effect>","overlay":0,"priority":50,"removeAtBattleEnd":true,"removeByDamage":false,"removeByRestriction":false,"removeByWalking":false,"restriction":0,"stepsToRemove":100},
{"id":45,"autoRemovalTiming":1,"chanceByDamage":100,"traits":[],"iconIndex":6,"maxTurns":1,"message1":"","message2":"","message3":"","message4":"","minTurns":1,"motion":0,"name":"Finished","note":"","overlay":0,"priority":50,"removeAtBattleEnd":true,"removeByDamage":false,"removeByRestriction":false,"removeByWalking":false,"restriction":0,"stepsToRemove":100},
{"id":46,"autoRemovalTiming":1,"chanceByDamage":100,"traits":[{"code":21,"dataId":5,"value":2},{"code":21,"dataId":6,"value":0.9},{"code":14,"dataId":40,"value":1},{"code":14,"dataId":42,"value":1},{"code":14,"dataId":43,"value":1},{"code":14,"dataId":44,"value":1}],"iconIndex":162,"maxTurns":2,"message1":"","message2":"","message3":"","message4":"","minTurns":2,"motion":0,"name":"Mag. Defend","note":"<Custom Respond Effect>\n  var action = user.currentAction();\n  var actionId = 10;\n  if (action || action.isMagical()) {\n      target.removeState(46);\n      target.addState(47);\n    }\n</Custom Respond Effect>\n<Category: Bypass Death Removal>","overlay":0,"priority":50,"removeAtBattleEnd":true,"removeByDamage":false,"removeByRestriction":false,"removeByWalking":false,"restriction":0,"stepsToRemove":100},
{"id":47,"autoRemovalTiming":1,"chanceByDamage":100,"traits":[{"code":21,"dataId":5,"value":2.5},{"code":21,"dataId":6,"value":0.8},{"code":14,"dataId":46,"value":1},{"code":14,"dataId":40,"value":1},{"code":14,"dataId":42,"value":1},{"code":14,"dataId":43,"value":1},{"code":14,"dataId":44,"value":1}],"iconIndex":163,"maxTurns":2,"message1":"","message2":"","message3":"","message4":"","minTurns":2,"motion":0,"name":"Mag. Def 2","note":"<Category: Bypass Death Removal>\n<Custom Respond Effect>\n  var action = user.currentAction();\n  var actionId = 10;\n  if (action || action.isMagical()) {\n      target.removeState(46);\n      target.removeState(47);\n      target.addState(48);\n    }\n</Custom Respond Effect>","overlay":0,"priority":50,"removeAtBattleEnd":true,"removeByDamage":false,"removeByRestriction":false,"removeByWalking":false,"restriction":0,"stepsToRemove":100},
{"id":48,"autoRemovalTiming":1,"chanceByDamage":100,"traits":[{"code":21,"dataId":5,"value":3},{"code":21,"dataId":6,"value":0.7},{"code":14,"dataId":46,"value":1},{"code":14,"dataId":40,"value":1},{"code":14,"dataId":42,"value":1},{"code":14,"dataId":43,"value":1},{"code":14,"dataId":44,"value":1}],"iconIndex":164,"maxTurns":2,"message1":"","message2":"","message3":"","message4":"","minTurns":2,"motion":0,"name":"Mag. Def 3","note":"<Category: Bypass Death Removal>\n<Custom Respond Effect>\n  var action = user.currentAction();\n  var actionId = 10;\n  if (action || action.isMagical()) {\n      target.removeState(46);\n      target.removeState(48);\n      target.addState(49);\n    }\n</Custom Respond Effect>","overlay":0,"priority":50,"removeAtBattleEnd":true,"removeByDamage":false,"removeByRestriction":false,"removeByWalking":false,"restriction":0,"stepsToRemove":100},
{"id":49,"autoRemovalTiming":1,"chanceByDamage":100,"traits":[{"code":21,"dataId":5,"value":3.5},{"code":21,"dataId":6,"value":0.6},{"code":14,"dataId":46,"value":1},{"code":14,"dataId":40,"value":1},{"code":14,"dataId":42,"value":1},{"code":14,"dataId":43,"value":1},{"code":14,"dataId":44,"value":1}],"iconIndex":165,"maxTurns":2,"message1":"","message2":"","message3":"","message4":"","minTurns":2,"motion":0,"name":"Mag. Def. 4","note":"<Category: Bypass Death Removal>\n<Custom Respond Effect>\n  var action = user.currentAction();\n  var actionId = 10;\n  if (action || action.isMagical()) {\n      target.removeState(49);\n      target.addState(40);\n    }\n</Custom Respond Effect>","overlay":0,"priority":50,"removeAtBattleEnd":true,"removeByDamage":false,"removeByRestriction":false,"removeByWalking":false,"restriction":0,"stepsToRemove":100},
{"id":50,"autoRemovalTiming":1,"chanceByDamage":100,"traits":[{"code":21,"dataId":4,"value":2},{"code":21,"dataId":6,"value":3}],"iconIndex":28,"maxTurns":2,"message1":"","message2":"","message3":"","message4":"","minTurns":2,"motion":0,"name":"Mag. Atk","note":"<Custom Action Start Effect>\n  var action = user.currentAction();\n  if (action.isMagical()) {\n      user.removeState(50);\n      user.addState(51);\n    }\n</Custom Action Start Effect>","overlay":0,"priority":50,"removeAtBattleEnd":true,"removeByDamage":false,"removeByRestriction":false,"removeByWalking":false,"restriction":0,"stepsToRemove":100},
{"id":51,"autoRemovalTiming":1,"chanceByDamage":100,"traits":[{"code":21,"dataId":4,"value":3},{"code":21,"dataId":6,"value":3.5},{"code":14,"dataId":50,"value":1}],"iconIndex":29,"maxTurns":2,"message1":"","message2":"","message3":"","message4":"","minTurns":2,"motion":0,"name":"Mag. Atk 2","note":"<Custom Action Start Effect>\n  var action = user.currentAction();\n  if (action.isMagical()) {\n      user.removeState(51);\n      user.addState(52);\n    }\n</Custom Action Start Effect>","overlay":0,"priority":50,"removeAtBattleEnd":true,"removeByDamage":false,"removeByRestriction":false,"removeByWalking":false,"restriction":0,"stepsToRemove":100},
{"id":52,"autoRemovalTiming":1,"chanceByDamage":100,"traits":[{"code":21,"dataId":4,"value":4.2},{"code":21,"dataId":6,"value":5},{"code":14,"dataId":50,"value":1}],"iconIndex":30,"maxTurns":2,"message1":"","message2":"","message3":"","message4":"","minTurns":2,"motion":0,"name":"Mag. Atk 3","note":"<Custom Action Start Effect>\n  var action = user.currentAction();\n  if (action.isMagical()) {\n      user.removeState(52);\n      user.addState(53);\n    }\n</Custom Action Start Effect>","overlay":0,"priority":50,"removeAtBattleEnd":true,"removeByDamage":false,"removeByRestriction":false,"removeByWalking":false,"restriction":0,"stepsToRemove":100},
{"id":53,"autoRemovalTiming":1,"chanceByDamage":100,"traits":[{"code":21,"dataId":4,"value":5},{"code":21,"dataId":6,"value":6},{"code":14,"dataId":50,"value":1}],"iconIndex":31,"maxTurns":2,"message1":"","message2":"","message3":"","message4":"","minTurns":2,"motion":0,"name":"Mag. Atk 4","note":"<Custom Action Start Effect>\n  var action = user.currentAction();\n  if (action.isMagical()) {\n      user.removeState(53);\n    }\n</Custom Action End Effect>\n\n<Custom Remove Effect>\nuser.removeState(37);\n</Custom Remove Effect>","overlay":0,"priority":50,"removeAtBattleEnd":true,"removeByDamage":false,"removeByRestriction":false,"removeByWalking":false,"restriction":0,"stepsToRemove":100},
{"id":54,"autoRemovalTiming":0,"chanceByDamage":100,"traits":[{"code":21,"dataId":2,"value":3},{"code":21,"dataId":6,"value":4},{"code":23,"dataId":5,"value":0.5}],"iconIndex":0,"maxTurns":1,"message1":"","message2":"","message3":"","message4":"","minTurns":1,"motion":0,"name":"Struggling","note":"<Custom Passive Condition>\nif (user.hp / user.mhp <= 0.3) {\ncondition = true;\n}\n else {\ncondition = false;\n}\n</Custom Passive Condition>","overlay":0,"priority":50,"removeAtBattleEnd":false,"removeByDamage":false,"removeByRestriction":false,"removeByWalking":false,"restriction":0,"stepsToRemove":100},
{"id":55,"autoRemovalTiming":0,"chanceByDamage":100,"traits":[{"code":14,"dataId":1,"value":1}],"iconIndex":0,"maxTurns":1,"message1":"","message2":"","message3":"","message4":"","minTurns":1,"motion":0,"name":"Immortal-Meiling","note":"<Custom Passive Condition>\nif (user.hp <= 0 && target.isStateAffected(10)) {\ncondition = false;\n}\n else {\ncondition = true;\n}\n</Custom Passive Condition>","overlay":0,"priority":50,"removeAtBattleEnd":true,"removeByDamage":false,"removeByRestriction":false,"removeByWalking":false,"restriction":0,"stepsToRemove":100},
{"id":56,"autoRemovalTiming":1,"chanceByDamage":100,"iconIndex":12,"maxTurns":3,"message1":" is fascinated!","message2":" is fascinated!","message3":"","message4":" is no longer fascinated!","minTurns":3,"motion":0,"name":"Lotus Palm","note":"<Custom Remove Effect>\nuser.addState(10);\nuser.addState(44);\n</Custom Remove Effect>","overlay":0,"priority":80,"releaseByDamage":false,"removeAtBattleEnd":true,"removeByDamage":false,"removeByRestriction":false,"removeByWalking":false,"restriction":0,"stepsToRemove":100,"traits":[{"code":32,"dataId":11,"value":1},{"code":21,"dataId":2,"value":4},{"code":21,"dataId":3,"value":10},{"code":21,"dataId":4,"value":10},{"code":44,"dataId":222,"value":1},{"code":44,"dataId":219,"value":1},{"code":44,"dataId":218,"value":1},{"code":22,"dataId":6,"value":2}]},
{"id":57,"autoRemovalTiming":1,"chanceByDamage":100,"traits":[{"code":44,"dataId":1,"value":1}],"iconIndex":0,"maxTurns":2,"message1":"","message2":"","message3":"","message4":"","minTurns":2,"motion":0,"name":"X-Seal","note":"","overlay":0,"priority":50,"removeAtBattleEnd":true,"removeByDamage":false,"removeByRestriction":false,"removeByWalking":false,"restriction":0,"stepsToRemove":100},
{"id":58,"autoRemovalTiming":1,"chanceByDamage":100,"traits":[{"code":42,"dataId":3,"value":1},{"code":42,"dataId":4,"value":1},{"code":42,"dataId":5,"value":1},{"code":42,"dataId":6,"value":1},{"code":42,"dataId":7,"value":1}],"iconIndex":0,"maxTurns":2,"message1":"","message2":"","message3":"","message4":"","minTurns":2,"motion":0,"name":"O-Seal","note":"","overlay":0,"priority":50,"removeAtBattleEnd":true,"removeByDamage":false,"removeByRestriction":false,"removeByWalking":false,"restriction":0,"stepsToRemove":100},
{"id":59,"autoRemovalTiming":2,"chanceByDamage":2,"traits":[{"code":44,"dataId":226,"value":1}],"iconIndex":0,"maxTurns":2,"message1":"","message2":"","message3":"","message4":"","minTurns":2,"motion":0,"name":"Blink","note":"\n<Custom Apply Effect>\n// Check if the user is an enemy.\nif (user.isEnemy()) {\n  // Archive the previous enemy ID.\n  user._prevEnemyId = user._enemyId;\n  // Set the target enemy ID you want the enemy to change into.\n  var transformEnemyId = 70;\n  // Transform the user.\n  user.transform(transformEnemyId);\n}\n</Custom Apply Effect>\n\n<Custom Remove Effect>\n// Check if the user is an enemy.\nif (user.isEnemy()) {\n  // Retrieve the archived enemy ID.\n  var transformEnemyId = user._prevEnemyId;\n  // Transform the enemy back.\n  user.transform(transformEnemyId);\n  // Clear the archived data.\n  user._prevEnemyId = undefined;\n}\n</Custom Remove Effect>\n\n// Selection Control\n<Cannot Select: All>","overlay":0,"priority":50,"removeAtBattleEnd":true,"removeByDamage":false,"removeByRestriction":false,"removeByWalking":false,"restriction":0,"stepsToRemove":100},
{"id":60,"autoRemovalTiming":1,"chanceByDamage":100,"iconIndex":8,"maxTurns":3,"message1":" falls asleep!","message2":" falls asleep!","message3":" is sleeping.","message4":" wakes up!","minTurns":3,"motion":2,"name":"Sleep","note":"<Category: Bypass Death Removal>","overlay":7,"priority":90,"releaseByDamage":true,"removeAtBattleEnd":true,"removeByDamage":true,"removeByRestriction":false,"removeByWalking":false,"restriction":4,"stepsToRemove":100,"traits":[{"code":22,"dataId":1,"value":-1}]},
{"id":61,"autoRemovalTiming":0,"chanceByDamage":100,"traits":[],"iconIndex":0,"maxTurns":1,"message1":"","message2":"","message3":"","message4":"","minTurns":1,"motion":0,"name":"Last Skill","note":"<Custom Passive Condition>\n\nif($gameParty.inBattle()){\n\ncondition = true;\n\n} else {\n\ncondition = false;\n\n}\n\n</Custom Passive Condition>\n\n<Custom Turn Start Effect>\n\nvar skillz = user._LastActionId || 0;\n\n</Custom Turn Start Effect>\n\n\n\n<Custom Remove Effect>\n\nvar skillz = 0;\n\n</Custom Remove Effect>\n\n\n\n<Custom Initiate Effect>\n\nvar action = user.currentAction();\n\nif (action && action.isSkill()) {\n\nactionId = action.item().id || 0;\n\nif(actionId != 231 || actionId != 7) {//Set X equal to your \"Keep Playing Skill\" that I'll discuss later.\n//You can also add \"|| actionId != x\" within the parentheses if there are other skills you don't want to be Encored.\nvar skillz = action.item().id;\n\n}\n\n}\n\n</Custom Initiate Effect>","overlay":0,"priority":50,"removeAtBattleEnd":true,"removeByDamage":false,"removeByRestriction":false,"removeByWalking":false,"restriction":0,"stepsToRemove":100},
{"id":62,"autoRemovalTiming":0,"chanceByDamage":100,"traits":[],"iconIndex":75,"maxTurns":1,"message1":"","message2":"","message3":"","message4":"","minTurns":1,"motion":0,"name":"Loop","note":"","overlay":0,"priority":50,"removeAtBattleEnd":true,"removeByDamage":false,"removeByRestriction":false,"removeByWalking":false,"restriction":0,"stepsToRemove":100},
{"id":63,"autoRemovalTiming":2,"chanceByDamage":100,"traits":[],"iconIndex":160,"maxTurns":2,"message1":"","message2":"","message3":"","message4":"","minTurns":2,"motion":0,"name":"Spitted","note":"<Custom Remove Effect>\nvar skill = 234;\nvar target = -2;\nBattleManager.queueForceAction(user, skill, target);\n</Custom Remove Effect>","overlay":0,"priority":50,"removeAtBattleEnd":true,"removeByDamage":false,"removeByRestriction":false,"removeByWalking":false,"restriction":0,"stepsToRemove":100},
{"id":64,"autoRemovalTiming":2,"chanceByDamage":100,"traits":[{"code":23,"dataId":5,"value":1.12},{"code":22,"dataId":7,"value":-0.12}],"iconIndex":0,"maxTurns":2,"message1":"","message2":"","message3":"","message4":"","minTurns":2,"motion":0,"name":"TP-Regen","note":"","overlay":0,"priority":50,"removeAtBattleEnd":true,"removeByDamage":false,"removeByRestriction":false,"removeByWalking":false,"restriction":0,"stepsToRemove":100},
{"id":65,"autoRemovalTiming":0,"chanceByDamage":100,"traits":[],"iconIndex":0,"maxTurns":1,"message1":"","message2":"","message3":"","message4":"","minTurns":1,"motion":0,"name":"Last","note":"<Category: Bypass Death Removal>\n<Custom Turn End Effect>\nuser.addState(44);\nuser.die();\n</Custom Turn End Effect>","overlay":0,"priority":50,"removeAtBattleEnd":false,"removeByDamage":false,"removeByRestriction":false,"removeByWalking":false,"restriction":0,"stepsToRemove":100},
{"id":66,"autoRemovalTiming":1,"chanceByDamage":100,"traits":[{"code":42,"dataId":3,"value":1},{"code":42,"dataId":4,"value":1},{"code":42,"dataId":5,"value":1},{"code":42,"dataId":6,"value":1},{"code":42,"dataId":7,"value":1}],"iconIndex":21,"maxTurns":2,"message1":"","message2":"","message3":"","message4":"","minTurns":2,"motion":0,"name":"Fantasy-Seal","note":"","overlay":0,"priority":50,"removeAtBattleEnd":true,"removeByDamage":true,"removeByRestriction":false,"removeByWalking":false,"restriction":0,"stepsToRemove":100},
{"id":67,"autoRemovalTiming":2,"chanceByDamage":0,"traits":[{"code":44,"dataId":226,"value":1},{"code":44,"dataId":5,"value":1},{"code":44,"dataId":20,"value":1},{"code":44,"dataId":236,"value":1}],"iconIndex":77,"maxTurns":2,"message1":"","message2":"","message3":"","message4":"","minTurns":2,"motion":0,"name":"FS-Rei","note":"// Buffs & States Core\n<Custom Leave Effect>\n// Get the landing skill.\nvar skill = 251;\n// Get the last targeted index.\nvar target = -2;\n// Queue the forced action.\nBattleManager.queueForceAction(user, skill, target);\n</Custom Leave Effect>","overlay":0,"priority":50,"removeAtBattleEnd":true,"removeByDamage":false,"removeByRestriction":false,"removeByWalking":false,"restriction":0,"stepsToRemove":100},
{"id":68,"autoRemovalTiming":0,"chanceByDamage":100,"traits":[{"code":42,"dataId":3,"value":1},{"code":42,"dataId":4,"value":1},{"code":42,"dataId":5,"value":1},{"code":42,"dataId":6,"value":1},{"code":42,"dataId":7,"value":1},{"code":43,"dataId":241,"value":1},{"code":44,"dataId":72,"value":1},{"code":44,"dataId":2,"value":1},{"code":44,"dataId":236,"value":1}],"iconIndex":161,"maxTurns":1,"message1":"","message2":"","message3":"","message4":"","minTurns":1,"motion":0,"name":"Ensnared","note":"","overlay":0,"priority":50,"removeAtBattleEnd":true,"removeByDamage":true,"removeByRestriction":false,"removeByWalking":false,"restriction":0,"stepsToRemove":100},
{"id":69,"autoRemovalTiming":2,"chanceByDamage":100,"traits":[{"code":43,"dataId":242,"value":1},{"code":21,"dataId":6,"value":0.5}],"iconIndex":23,"maxTurns":2,"message1":"","message2":"","message3":"","message4":"","minTurns":2,"motion":0,"name":"Poison Web","note":"\n\n<Custom Decay Effect>\nuser.addState(4);\n</Custom Decay Effect>","overlay":0,"priority":50,"removeAtBattleEnd":true,"removeByDamage":true,"removeByRestriction":false,"removeByWalking":false,"restriction":0,"stepsToRemove":100},
{"id":70,"autoRemovalTiming":0,"chanceByDamage":100,"traits":[{"code":44,"dataId":226,"value":1},{"code":43,"dataId":235,"value":1}],"iconIndex":0,"maxTurns":1,"message1":"","message2":"","message3":"","message4":"","minTurns":1,"motion":0,"name":"FS-Rei2","note":"","overlay":0,"priority":50,"removeAtBattleEnd":true,"removeByDamage":false,"removeByRestriction":false,"removeByWalking":false,"restriction":0,"stepsToRemove":100},
{"id":71,"autoRemovalTiming":2,"chanceByDamage":100,"traits":[{"code":21,"dataId":5,"value":2},{"code":21,"dataId":3,"value":2}],"iconIndex":87,"maxTurns":3,"message1":"","message2":"","message3":"","message4":"","minTurns":3,"motion":0,"name":"Roost - A","note":"","overlay":0,"priority":50,"removeAtBattleEnd":true,"removeByDamage":false,"removeByRestriction":true,"removeByWalking":false,"restriction":0,"stepsToRemove":100},
{"id":72,"autoRemovalTiming":2,"chanceByDamage":100,"traits":[{"code":43,"dataId":245,"value":1}],"iconIndex":89,"maxTurns":2,"message1":"","message2":"","message3":"","message4":"","minTurns":2,"motion":0,"name":"Roost - B","note":"<Battle Commands>\nSkill:245\n</Battle Commands>","overlay":0,"priority":50,"removeAtBattleEnd":true,"removeByDamage":false,"removeByRestriction":false,"removeByWalking":false,"restriction":0,"stepsToRemove":100},
{"id":73,"autoRemovalTiming":2,"chanceByDamage":100,"traits":[{"code":22,"dataId":1,"value":-1},{"code":22,"dataId":4,"value":-1}],"iconIndex":88,"maxTurns":2,"message1":"","message2":"","message3":"","message4":"","minTurns":2,"motion":0,"name":"Grounded","note":"","overlay":0,"priority":50,"removeAtBattleEnd":true,"removeByDamage":false,"removeByRestriction":false,"removeByWalking":false,"restriction":0,"stepsToRemove":100},
{"id":74,"autoRemovalTiming":1,"chanceByDamage":100,"traits":[{"code":14,"dataId":13,"value":1}],"iconIndex":0,"maxTurns":1,"message1":"","message2":"","message3":"","message4":"","minTurns":1,"motion":0,"name":"Protect","note":"<Restrict>\nSkill:51\nSkill:52\n</Restrict>","overlay":0,"priority":50,"removeAtBattleEnd":true,"removeByDamage":false,"removeByRestriction":false,"removeByWalking":false,"restriction":0,"stepsToRemove":100},
{"id":75,"autoRemovalTiming":1,"chanceByDamage":100,"traits":[{"code":14,"dataId":14,"value":1}],"iconIndex":0,"maxTurns":1,"message1":"","message2":"","message3":"","message4":"","minTurns":1,"motion":0,"name":"Barrier","note":"<Restrict>\nSkill:53\nSkill:54\n</Restrict>","overlay":0,"priority":50,"removeAtBattleEnd":true,"removeByDamage":false,"removeByRestriction":false,"removeByWalking":false,"restriction":0,"stepsToRemove":100},
{"id":76,"autoRemovalTiming":0,"chanceByDamage":100,"traits":[{"code":44,"dataId":239,"value":1},{"code":44,"dataId":238,"value":1},{"code":44,"dataId":240,"value":1}],"iconIndex":27,"maxTurns":1,"message1":"","message2":"","message3":"","message4":"","minTurns":1,"motion":0,"name":"Yamame-State 1","note":"<Custom Passive Condition>\nif (user.hp / user.mhp >= 0.9) {\n    condition = true;\n  } else {\n    condition = false;\n  }\n</Custom Passive Condition>","overlay":0,"priority":50,"removeAtBattleEnd":false,"removeByDamage":false,"removeByRestriction":false,"removeByWalking":false,"restriction":0,"stepsToRemove":100},
{"id":77,"autoRemovalTiming":0,"chanceByDamage":100,"traits":[],"iconIndex":11,"maxTurns":1,"message1":"","message2":"","message3":"","message4":"","minTurns":1,"motion":0,"name":"Yamame-State 2","note":"<Custom Passive Condition>\nif (user.hp / user.mhp < 0.9) {\n    condition = true;\n  } else {\n    condition = false;\n  }\n</Custom Passive Condition>","overlay":0,"priority":50,"removeAtBattleEnd":false,"removeByDamage":false,"removeByRestriction":false,"removeByWalking":false,"restriction":0,"stepsToRemove":100},
{"id":78,"autoRemovalTiming":2,"chanceByDamage":100,"traits":[{"code":44,"dataId":238,"value":1},{"code":44,"dataId":239,"value":1}],"iconIndex":26,"maxTurns":2,"message1":"","message2":"","message3":"","message4":"","minTurns":2,"motion":0,"name":"Web-Stinged","note":"","overlay":0,"priority":50,"removeAtBattleEnd":false,"removeByDamage":false,"removeByRestriction":false,"removeByWalking":false,"restriction":0,"stepsToRemove":100},
{"id":79,"autoRemovalTiming":0,"chanceByDamage":100,"traits":[{"code":44,"dataId":226,"value":1},{"code":44,"dataId":236,"value":1},{"code":44,"dataId":1,"value":1}],"iconIndex":18,"maxTurns":1,"message1":"","message2":"","message3":"","message4":"","minTurns":1,"motion":0,"name":"Rei-State 1","note":"<Custom Passive Condition>\nif (user.hp / user.mhp >= 0.95) {\n    condition = true;\n  } else {\n    condition = false;\n  }\n</Custom Passive Condition>","overlay":0,"priority":50,"removeAtBattleEnd":true,"removeByDamage":false,"removeByRestriction":false,"removeByWalking":false,"restriction":0,"stepsToRemove":100},
{"id":80,"autoRemovalTiming":0,"chanceByDamage":100,"traits":[{"code":44,"dataId":20,"value":1}],"iconIndex":0,"maxTurns":1,"message1":"","message2":"","message3":"","message4":"","minTurns":1,"motion":0,"name":"Rei-State 2","note":"<Custom Passive Condition>\nif (user.mp / user.mmp < 0.95) {\n    condition = true;\n  } else {\n    condition = false;\n  }\n</Custom Passive Condition>","overlay":0,"priority":50,"removeAtBattleEnd":true,"removeByDamage":false,"removeByRestriction":false,"removeByWalking":false,"restriction":0,"stepsToRemove":100},
{"id":81,"autoRemovalTiming":0,"chanceByDamage":100,"traits":[{"code":44,"dataId":20,"value":1}],"iconIndex":0,"maxTurns":1,"message1":"","message2":"","message3":"","message4":"","minTurns":1,"motion":0,"name":"Rei-State 3","note":"<Custom Passive Condition>\nif (user.hp / user.mhp < 0.8) {\n    condition = true;\n  } else {\n    condition = false;\n  }\n</Custom Passive Condition>","overlay":0,"priority":50,"removeAtBattleEnd":true,"removeByDamage":false,"removeByRestriction":false,"removeByWalking":false,"restriction":0,"stepsToRemove":100},
{"id":82,"autoRemovalTiming":2,"chanceByDamage":100,"traits":[{"code":44,"dataId":226,"value":1}],"iconIndex":20,"maxTurns":1,"message1":"","message2":"","message3":"","message4":"","minTurns":1,"motion":0,"name":"Blink - Cooldown","note":"","overlay":0,"priority":50,"removeAtBattleEnd":true,"removeByDamage":false,"removeByRestriction":false,"removeByWalking":false,"restriction":0,"stepsToRemove":100},
{"id":83,"autoRemovalTiming":2,"chanceByDamage":100,"description":"","iconIndex":0,"maxTurns":1,"message1":"","message2":"","message3":"","message4":"","minTurns":1,"motion":0,"name":"Immortal","note":"","overlay":0,"priority":0,"removeAtBattleEnd":true,"removeByDamage":false,"removeByRestriction":true,"removeByWalking":false,"restriction":0,"stepsToRemove":100,"traits":[{"code":14,"dataId":1,"value":0}]},
{"id":84,"autoRemovalTiming":2,"chanceByDamage":100,"traits":[{"code":43,"dataId":228,"value":1},{"code":22,"dataId":8,"value":-0.3},{"code":22,"dataId":1,"value":1},{"code":22,"dataId":4,"value":1},{"code":22,"dataId":9,"value":0.2}],"iconIndex":0,"maxTurns":3,"message1":"","message2":"","message3":"","message4":"","minTurns":3,"motion":0,"name":"Blink 2","note":"<Custom Apply Effect>\n// Check if user is an actor.\nif (user.isActor()) {\n  // Archive the previous settings.\n  user._prevCharName = user._prevCharName || user._characterName;\n  user._prevCharIndex = user._prevCharIndex || user._characterIndex;\n  user._prevFaceName = user._prevFaceName || user._faceName;\n  user._prevFaceIndex = user._prevFaceIndex || user._faceIndex;\n  user._prevBattlerName = user._prevBattlerName || user._battlerName;\n  // Check if the actor ID is 1.\n  if (user.actorId() === 2) {\n    // The filename of the character graphic without the file extension.\n    var charName = 'rei';\n    // The index of the character graphic used.\n    var charIndex = 0;\n    // The filename of the face graphic without the file extension.\n    var faceName = 'thfs';\n    // The index of of the face graphic used.\n    var faceIndex = 0;\n    // The filename of the battler graphic without the file extension.\n    var battlerName = 'rei-blink';\n  } \n  // Changes the character image to the setting applied from above.\n  user.setCharacterImage(charName, charIndex);\n  // Changes the face image to the setting applied from above.\n  user.setFaceImage(faceName, faceIndex);\n  // Changes the battler image from the setting applied from above.\n  user.setBattlerImage(battlerName);\n  // Refreshes the user's appearance.\n  user.refresh();\n}\n</Custom Apply Effect>\n\n<Custom Remove Effect>\n// Retrieve archived settings.\nvar charName = user._prevCharName;\nvar charIndex = user._prevCharIndex;\nvar faceName = user._prevFaceName;\nvar faceIndex = user._prevFaceIndex;\nvar battlerName = user._prevBattlerName;\n// Changes the character image to the archived setting.\nuser.setCharacterImage(charName, charIndex);\n// Changes the face image to the archived setting.\nuser.setFaceImage(faceName, faceIndex);\n// Changes the battler image from the archived setting.\nuser.setBattlerImage(battlerName);\n// Clear archived data.\nuser._priorityCharacterName = undefined;\nuser._priorityCharacterIndex = undefined;\nuser._prevFaceName = undefined;\nuser._prevFaceIndex = undefined;\nuser._priorityFaceName = undefined;\nuser._priorityFaceIndex = undefined;\nuser._prevFaceName = undefined;\nuser._prevFaceIndex = undefined;\nuser._priorityBattlerName = undefined;\nuser._prevBattlerName = undefined;\n// Refreshes the user's appearance.\nuser.refresh();\n</Custom Remove Effect>\n\n<Cannot Select: All>","overlay":0,"priority":50,"removeAtBattleEnd":true,"removeByDamage":false,"removeByRestriction":false,"removeByWalking":false,"restriction":0,"stepsToRemove":100},
{"id":85,"autoRemovalTiming":1,"chanceByDamage":100,"traits":[],"iconIndex":0,"maxTurns":2,"message1":"","message2":"","message3":"","message4":"","minTurns":2,"motion":0,"name":"FSRei2","note":"","overlay":0,"priority":50,"removeAtBattleEnd":false,"removeByDamage":false,"removeByRestriction":false,"removeByWalking":false,"restriction":0,"stepsToRemove":100},
{"id":86,"autoRemovalTiming":0,"chanceByDamage":100,"traits":[{"code":44,"dataId":218,"value":1},{"code":44,"dataId":219,"value":1},{"code":44,"dataId":220,"value":1},{"code":44,"dataId":221,"value":1}],"iconIndex":0,"maxTurns":1,"message1":"","message2":"","message3":"","message4":"","minTurns":1,"motion":0,"name":"Meiling State 1","note":"","overlay":0,"priority":50,"removeAtBattleEnd":false,"removeByDamage":false,"removeByRestriction":false,"removeByWalking":false,"restriction":0,"stepsToRemove":100},
{"id":87,"autoRemovalTiming":0,"chanceByDamage":100,"traits":[{"code":44,"dataId":10,"value":1}],"iconIndex":0,"maxTurns":1,"message1":"","message2":"","message3":"","message4":"","minTurns":1,"motion":0,"name":"Meiling State 2","note":"","overlay":0,"priority":50,"removeAtBattleEnd":false,"removeByDamage":false,"removeByRestriction":false,"removeByWalking":false,"restriction":0,"stepsToRemove":100},
{"id":88,"autoRemovalTiming":0,"chanceByDamage":100,"traits":[],"iconIndex":0,"maxTurns":1,"message1":"","message2":"","message3":"","message4":"","minTurns":1,"motion":0,"name":"Meiling State 3","note":"","overlay":0,"priority":50,"removeAtBattleEnd":false,"removeByDamage":false,"removeByRestriction":false,"removeByWalking":false,"restriction":0,"stepsToRemove":100},
{"id":89,"autoRemovalTiming":0,"chanceByDamage":100,"traits":[{"code":22,"dataId":4,"value":1},{"code":44,"dataId":21,"value":1},{"code":44,"dataId":11,"value":1}],"iconIndex":1,"maxTurns":1,"message1":"","message2":"","message3":"","message4":"","minTurns":1,"motion":0,"name":"Remi - Transform","note":"<Custom Passive Condition>\nif (user.isStateAffected(40)) {\n    condition = true;\nif (user.isEnemy()) {\n  // Archive the previous enemy ID.\n  user._prevEnemyId = user._enemyId;\n  // Set the target enemy ID you want the enemy to change into.\n  var transformEnemyId = 68;\n  // Transform the user.\n  user.transform(transformEnemyId);\n}\n  } else {\n    condition = false;\n}\n</Custom Passive Condition>\n\n<Custom Apply Effect>\n// Check if the user is an enemy.\nif (user.isEnemy()) {\n  // Archive the previous enemy ID.\n  user._prevEnemyId = user._enemyId;\n  // Set the target enemy ID you want the enemy to change into.\n  var transformEnemyId = 68;\n  // Transform the user.\n  user.transform(transformEnemyId);\n}\n</Custom Apply Effect>\n\n<Custom Remove Effect>\n// Check if the user is an enemy.\nif (user.isEnemy()) {\n  // Retrieve the archived enemy ID.\n  var transformEnemyId = user._prevEnemyId;\n  // Transform the enemy back.\n  user.transform(transformEnemyId);\n  // Clear the archived data.\n  user._prevEnemyId = undefined;\n}\n</Custom Remove Effect>","overlay":0,"priority":50,"removeAtBattleEnd":false,"removeByDamage":false,"removeByRestriction":false,"removeByWalking":false,"restriction":0,"stepsToRemove":100},
{"id":90,"autoRemovalTiming":0,"chanceByDamage":100,"traits":[],"iconIndex":17,"maxTurns":1,"message1":"","message2":"","message3":"","message4":"","minTurns":1,"motion":0,"name":"Remi - Transform 2","note":"<Custom Passive Condition>\nif (!user.isStateAffected(40)) {\n    condition = true;\nif (user.isEnemy()) {\n  // Archive the previous enemy ID.\n  user._prevEnemyId = user._enemyId;\n  // Set the target enemy ID you want the enemy to change into.\n  var transformEnemyId = 39;\n  // Transform the user.\n  user.transform(transformEnemyId);\n}\n  } else {\n    condition = false;\n}\n</Custom Passive Condition>","overlay":0,"priority":50,"removeAtBattleEnd":false,"removeByDamage":false,"removeByRestriction":false,"removeByWalking":false,"restriction":0,"stepsToRemove":100},
{"id":91,"autoRemovalTiming":0,"chanceByDamage":100,"traits":[],"iconIndex":0,"maxTurns":1,"message1":"","message2":"","message3":"","message4":"","minTurns":1,"motion":0,"name":"Remi - State 1","note":"","overlay":0,"priority":50,"removeAtBattleEnd":false,"removeByDamage":false,"removeByRestriction":false,"removeByWalking":false,"restriction":0,"stepsToRemove":100},
{"id":92,"autoRemovalTiming":0,"chanceByDamage":100,"traits":[],"iconIndex":0,"maxTurns":1,"message1":"","message2":"","message3":"","message4":"","minTurns":1,"motion":0,"name":"Remi - State 2","note":"","overlay":0,"priority":50,"removeAtBattleEnd":false,"removeByDamage":false,"removeByRestriction":false,"removeByWalking":false,"restriction":0,"stepsToRemove":100},
{"id":93,"autoRemovalTiming":1,"chanceByDamage":100,"traits":[{"code":22,"dataId":4,"value":1},{"code":22,"dataId":1,"value":1}],"iconIndex":0,"maxTurns":2,"message1":"","message2":"","message3":"","message4":"","minTurns":2,"motion":0,"name":"Sakuya - Time Leap","note":"<Cannot Select: All>\n\n<Custom Apply Effect>\n// Check if the user is an enemy.\nif (user.isEnemy()) {\n  // Archive the previous enemy ID.\n  user._prevEnemyId = user._enemyId;\n  // Set the target enemy ID you want the enemy to change into.\n  var transformEnemyId = 69;\n  // Transform the user.\n  user.transform(transformEnemyId);\n}\n</Custom Apply Effect>\n\n<Custom Remove Effect>\n// Check if the user is an enemy.\nif (user.isEnemy()) {\n  // Retrieve the archived enemy ID.\n  var transformEnemyId = user._prevEnemyId;\n  // Transform the enemy back.\n  user.transform(transformEnemyId);\n  // Clear the archived data.\n  user._prevEnemyId = undefined;\n}\n</Custom Remove Effect>","overlay":0,"priority":50,"removeAtBattleEnd":true,"removeByDamage":false,"removeByRestriction":false,"removeByWalking":false,"restriction":0,"stepsToRemove":100},
{"id":94,"autoRemovalTiming":0,"chanceByDamage":100,"traits":[{"code":22,"dataId":1,"value":-0.95}],"iconIndex":0,"maxTurns":1,"message1":"","message2":"","message3":"","message4":"","minTurns":1,"motion":0,"name":"Spectre - Transform 1","note":"<Custom Passive Condition>\nif (user.isStateAffected(40)) {\n    condition = true;\n  } else {\n    condition = false;\n}\n</Custom Passive Condition>","overlay":0,"priority":50,"removeAtBattleEnd":false,"removeByDamage":false,"removeByRestriction":false,"removeByWalking":false,"restriction":0,"stepsToRemove":100},
{"id":95,"autoRemovalTiming":0,"chanceByDamage":100,"traits":[],"iconIndex":0,"maxTurns":1,"message1":"","message2":"","message3":"","message4":"","minTurns":1,"motion":0,"name":"Charged","note":"","overlay":0,"priority":50,"removeAtBattleEnd":false,"removeByDamage":false,"removeByRestriction":false,"removeByWalking":false,"restriction":0,"stepsToRemove":100},
{"id":96,"autoRemovalTiming":0,"chanceByDamage":100,"traits":[],"iconIndex":1,"maxTurns":1,"message1":"","message2":"","message3":"","message4":"","minTurns":1,"motion":0,"name":"Extracted","note":"","overlay":0,"priority":50,"removeAtBattleEnd":false,"removeByDamage":false,"removeByRestriction":false,"removeByWalking":false,"restriction":0,"stepsToRemove":100},
{"id":97,"autoRemovalTiming":0,"chanceByDamage":100,"traits":[{"code":22,"dataId":1,"value":1},{"code":11,"dataId":5,"value":2},{"code":21,"dataId":4,"value":5}],"iconIndex":69,"maxTurns":1,"message1":"","message2":"","message3":"","message4":"","minTurns":1,"motion":0,"name":"Windshield","note":"","overlay":0,"priority":50,"removeAtBattleEnd":false,"removeByDamage":true,"removeByRestriction":false,"removeByWalking":false,"restriction":0,"stepsToRemove":100},
{"id":98,"autoRemovalTiming":0,"chanceByDamage":100,"traits":[{"code":44,"dataId":228,"value":1}],"iconIndex":0,"maxTurns":1,"message1":"","message2":"","message3":"","message4":"","minTurns":1,"motion":0,"name":"Rei-State 5","note":"<Custom Passive Condition>\nif (!user.isStateAffected(59)) {\n    condition = true;\n  } else {\n    condition = false;\n  }\n</Custom Passive Condition>","overlay":0,"priority":50,"removeAtBattleEnd":false,"removeByDamage":false,"removeByRestriction":false,"removeByWalking":false,"restriction":0,"stepsToRemove":100},
{"id":99,"autoRemovalTiming":0,"chanceByDamage":100,"traits":[],"iconIndex":11,"maxTurns":1,"message1":"","message2":"","message3":"","message4":"","minTurns":1,"motion":0,"name":"Junctioned","note":"","overlay":0,"priority":50,"removeAtBattleEnd":false,"removeByDamage":false,"removeByRestriction":false,"removeByWalking":false,"restriction":0,"stepsToRemove":100},
{"id":100,"autoRemovalTiming":0,"chanceByDamage":50,"traits":[{"code":44,"dataId":256,"value":1}],"iconIndex":0,"maxTurns":1,"message1":"","message2":"","message3":"","message4":"","minTurns":1,"motion":0,"name":"Junctioned-Aunn","note":"","overlay":0,"priority":50,"removeAtBattleEnd":false,"removeByDamage":true,"removeByRestriction":false,"removeByWalking":false,"restriction":0,"stepsToRemove":100},
{"id":101,"autoRemovalTiming":0,"chanceByDamage":34,"traits":[{"code":44,"dataId":259,"value":1}],"iconIndex":39,"maxTurns":1,"message1":"","message2":"","message3":"","message4":"","minTurns":1,"motion":0,"name":"Burrow-Suwako","note":"\n<Custom Apply Effect>\n// Check if the user is an enemy.\nif (user.isEnemy()) {\n  // Archive the previous enemy ID.\n  user._prevEnemyId = user._enemyId;\n  // Set the target enemy ID you want the enemy to change into.\n  var transformEnemyId = 57;\n  // Transform the user.\n  user.transform(transformEnemyId);\n}\n</Custom Apply Effect>\n\n<Custom Remove Effect>\n// Check if the user is an enemy.\nif (user.isEnemy()) {\n  // Retrieve the archived enemy ID.\n  var transformEnemyId = user._prevEnemyId;\n  // Transform the enemy back.\n  user.transform(transformEnemyId);\n  // Clear the archived data.\n  user._prevEnemyId = undefined;\n}\n</Custom Remove Effect>","overlay":0,"priority":50,"removeAtBattleEnd":false,"removeByDamage":true,"removeByRestriction":false,"removeByWalking":false,"restriction":0,"stepsToRemove":100},
{"id":102,"autoRemovalTiming":1,"chanceByDamage":100,"traits":[],"iconIndex":11,"maxTurns":2,"message1":"","message2":"","message3":"","message4":"","minTurns":2,"motion":0,"name":"Rained","note":"","overlay":0,"priority":50,"removeAtBattleEnd":true,"removeByDamage":true,"removeByRestriction":false,"removeByWalking":false,"restriction":0,"stepsToRemove":100},
{"id":103,"autoRemovalTiming":1,"chanceByDamage":100,"traits":[{"code":14,"dataId":106,"value":1}],"iconIndex":68,"maxTurns":2,"message1":"","message2":"","message3":"","message4":"","minTurns":2,"motion":0,"name":"Earthed","note":"","overlay":0,"priority":50,"removeAtBattleEnd":true,"removeByDamage":true,"removeByRestriction":false,"removeByWalking":false,"restriction":0,"stepsToRemove":100},
{"id":104,"autoRemovalTiming":0,"chanceByDamage":100,"traits":[{"code":44,"dataId":260,"value":1},{"code":44,"dataId":261,"value":1}],"iconIndex":10,"maxTurns":1,"message1":"","message2":"","message3":"","message4":"","minTurns":1,"motion":0,"name":"Suwako Stage 2","note":"<Custom Passive Condition>\nif (user.hp / user.mhp < 0.5) {\n    condition = true;\n  } else {\n    condition = false;\n  }\n</Custom Passive Condition>","overlay":0,"priority":50,"removeAtBattleEnd":false,"removeByDamage":false,"removeByRestriction":false,"removeByWalking":false,"restriction":0,"stepsToRemove":100},
{"id":105,"autoRemovalTiming":0,"chanceByDamage":100,"traits":[{"code":44,"dataId":262,"value":1},{"code":44,"dataId":263,"value":1}],"iconIndex":110,"maxTurns":1,"message1":"","message2":"","message3":"","message4":"","minTurns":1,"motion":0,"name":"Suwako Stage 1","note":"<Custom Passive Condition>\nif (user.hp / user.mhp >= 0.5) {\n    condition = true;\n  } else {\n    condition = false;\n  }\n</Custom Passive Condition>","overlay":0,"priority":50,"removeAtBattleEnd":false,"removeByDamage":false,"removeByRestriction":false,"removeByWalking":false,"restriction":0,"stepsToRemove":100},
{"id":106,"autoRemovalTiming":0,"chanceByDamage":100,"traits":[{"code":22,"dataId":7,"value":-0.5}],"iconIndex":171,"maxTurns":1,"message1":"","message2":"","message3":"","message4":"","minTurns":1,"motion":0,"name":"Native Vapour","note":"<Custom Passive Condition>\nif (!user.isStateAffected(101)) {\n    condition = true;\n  } else {\n    condition = false;\n  }\n</Custom Passive Condition>","overlay":0,"priority":50,"removeAtBattleEnd":true,"removeByDamage":false,"removeByRestriction":false,"removeByWalking":false,"restriction":0,"stepsToRemove":100},
{"id":107,"autoRemovalTiming":0,"chanceByDamage":100,"traits":[{"code":21,"dataId":3,"value":0.5},{"code":21,"dataId":2,"value":2}],"iconIndex":0,"maxTurns":1,"message1":"","message2":"","message3":"","message4":"","minTurns":1,"motion":0,"name":"AdamantHelix","note":"","overlay":0,"priority":50,"removeAtBattleEnd":false,"removeByDamage":false,"removeByRestriction":false,"removeByWalking":false,"restriction":2,"stepsToRemove":100},
{"id":108,"autoRemovalTiming":0,"chanceByDamage":100,"traits":[{"code":21,"dataId":2,"value":5},{"code":21,"dataId":3,"value":5},{"code":21,"dataId":4,"value":0.1},{"code":21,"dataId":5,"value":0.1}],"iconIndex":97,"maxTurns":1,"message1":"","message2":"","message3":"","message4":"","minTurns":1,"motion":0,"name":"SatoriState2","note":"<Custom Passive Condition>\nif (!user.isStateAffected(40)) {\n    condition = true;\n  } else {\n    condition = false;\n  }\n</Custom Passive Condition>","overlay":0,"priority":50,"removeAtBattleEnd":true,"removeByDamage":false,"removeByRestriction":false,"removeByWalking":false,"restriction":0,"stepsToRemove":100},
{"id":109,"autoRemovalTiming":0,"chanceByDamage":100,"traits":[{"code":21,"dataId":2,"value":0.1},{"code":21,"dataId":3,"value":0.1},{"code":21,"dataId":4,"value":5},{"code":21,"dataId":5,"value":5},{"code":44,"dataId":5,"value":1},{"code":44,"dataId":272,"value":1}],"iconIndex":0,"maxTurns":1,"message1":"","message2":"","message3":"","message4":"","minTurns":1,"motion":0,"name":"SatoriState","note":"<Custom Passive Condition>\nif (user.isStateAffected(40)) {\n    condition = true;\n  } else {\n    condition = false;\n  }\n</Custom Passive Condition>","overlay":0,"priority":50,"removeAtBattleEnd":false,"removeByDamage":false,"removeByRestriction":false,"removeByWalking":false,"restriction":0,"stepsToRemove":100},
{"id":110,"autoRemovalTiming":0,"chanceByDamage":100,"traits":[{"code":21,"dataId":4,"value":5},{"code":21,"dataId":5,"value":5},{"code":21,"dataId":2,"value":0.1},{"code":21,"dataId":3,"value":0.1},{"code":14,"dataId":108,"value":1}],"iconIndex":79,"maxTurns":1,"message1":"","message2":"","message3":"","message4":"","minTurns":1,"motion":0,"name":"SatoriState3","note":"<Custom Passive Condition>\nif (user.isStateAffected(40)) {\n    condition = true;\n  } else {\n    condition = false;\n  }\n</Custom Passive Condition>","overlay":0,"priority":50,"removeAtBattleEnd":false,"removeByDamage":false,"removeByRestriction":false,"removeByWalking":false,"restriction":0,"stepsToRemove":100},
{"id":111,"autoRemovalTiming":0,"chanceByDamage":100,"traits":[{"code":21,"dataId":2,"value":0.5},{"code":21,"dataId":3,"value":0.5},{"code":21,"dataId":4,"value":0.5},{"code":21,"dataId":5,"value":0.5}],"iconIndex":315,"maxTurns":1,"message1":"","message2":"","message3":"","message4":"","minTurns":1,"motion":0,"name":"Radioactive","note":"","overlay":0,"priority":50,"removeAtBattleEnd":true,"removeByDamage":false,"removeByRestriction":false,"removeByWalking":false,"restriction":0,"stepsToRemove":100},
{"id":112,"autoRemovalTiming":0,"chanceByDamage":100,"traits":[],"iconIndex":302,"maxTurns":1,"message1":"","message2":"","message3":"","message4":"","minTurns":1,"motion":0,"name":"Radio-Okuu","note":"","overlay":0,"priority":50,"removeAtBattleEnd":false,"removeByDamage":true,"removeByRestriction":false,"removeByWalking":false,"restriction":0,"stepsToRemove":100},
{"id":113,"autoRemovalTiming":0,"chanceByDamage":100,"traits":[{"code":44,"dataId":7,"value":1},{"code":21,"dataId":5,"value":9},{"code":22,"dataId":7,"value":0.2},{"code":21,"dataId":3,"value":9}],"iconIndex":96,"maxTurns":1,"message1":"","message2":"","message3":"","message4":"","minTurns":1,"motion":0,"name":"GodEmperorTrump","note":"","overlay":0,"priority":50,"removeAtBattleEnd":false,"removeByDamage":true,"removeByRestriction":false,"removeByWalking":false,"restriction":4,"stepsToRemove":100},
{"id":114,"autoRemovalTiming":0,"chanceByDamage":100,"traits":[{"code":21,"dataId":2,"value":9},{"code":21,"dataId":3,"value":0.25},{"code":22,"dataId":7,"value":0.05}],"iconIndex":106,"maxTurns":1,"message1":"","message2":"","message3":"","message4":"","minTurns":1,"motion":0,"name":"GodEmperorTrump2","note":"","overlay":0,"priority":50,"removeAtBattleEnd":false,"removeByDamage":false,"removeByRestriction":false,"removeByWalking":false,"restriction":0,"stepsToRemove":100},
{"id":115,"autoRemovalTiming":0,"chanceByDamage":100,"traits":[{"code":44,"dataId":280,"value":1}],"iconIndex":0,"maxTurns":1,"message1":"","message2":"","message3":"","message4":"","minTurns":1,"motion":0,"name":"FOAK","note":"","overlay":0,"priority":50,"removeAtBattleEnd":false,"removeByDamage":false,"removeByRestriction":false,"removeByWalking":false,"restriction":0,"stepsToRemove":100},
{"id":116,"autoRemovalTiming":0,"chanceByDamage":100,"traits":[{"code":44,"dataId":281,"value":1}],"iconIndex":85,"maxTurns":1,"message1":"","message2":"","message3":"","message4":"","minTurns":1,"motion":0,"name":"CT","note":"","overlay":0,"priority":50,"removeAtBattleEnd":false,"removeByDamage":false,"removeByRestriction":false,"removeByWalking":false,"restriction":0,"stepsToRemove":100},
{"id":117,"autoRemovalTiming":0,"chanceByDamage":100,"traits":[],"iconIndex":85,"maxTurns":1,"message1":"","message2":"","message3":"","message4":"","minTurns":1,"motion":0,"name":"CT2","note":"","overlay":0,"priority":50,"removeAtBattleEnd":false,"removeByDamage":false,"removeByRestriction":false,"removeByWalking":false,"restriction":0,"stepsToRemove":100},
{"id":118,"autoRemovalTiming":0,"chanceByDamage":100,"traits":[{"code":22,"dataId":5,"value":1},{"code":44,"dataId":283,"value":1}],"iconIndex":0,"maxTurns":1,"message1":"","message2":"","message3":"","message4":"","minTurns":1,"motion":0,"name":"Catadioptric","note":"","overlay":0,"priority":50,"removeAtBattleEnd":false,"removeByDamage":false,"removeByRestriction":false,"removeByWalking":false,"restriction":0,"stepsToRemove":100},
{"id":119,"autoRemovalTiming":0,"chanceByDamage":100,"traits":[{"code":22,"dataId":4,"value":1},{"code":44,"dataId":21,"value":1},{"code":44,"dataId":11,"value":1},{"code":22,"dataId":1,"value":1}],"iconIndex":1,"maxTurns":1,"message1":"","message2":"","message3":"","message4":"","minTurns":1,"motion":0,"name":"Flan - Transform","note":"<Custom Passive Condition>\nif (user.isStateAffected(40) && user.hp / user.mhp < 0.3) {\n    condition = true;\nif (user.isEnemy()) {\n  // Archive the previous enemy ID.\n  user._prevEnemyId = user._enemyId;\n  // Set the target enemy ID you want the enemy to change into.\n  var transformEnemyId = 64;\n  // Transform the user.\n  user.transform(transformEnemyId);\n}\n  } else {\n    condition = false;\n}\n</Custom Passive Condition>\n\n<Custom Apply Effect>\n// Check if the user is an enemy.\nif (user.isEnemy()) {\n  // Archive the previous enemy ID.\n  user._prevEnemyId = user._enemyId;\n  // Set the target enemy ID you want the enemy to change into.\n  var transformEnemyId = 68;\n  // Transform the user.\n  user.transform(transformEnemyId);\n}\n</Custom Apply Effect>\n\n<Custom Remove Effect>\n// Check if the user is an enemy.\nif (user.isEnemy()) {\n  // Retrieve the archived enemy ID.\n  var transformEnemyId = user._prevEnemyId;\n  // Transform the enemy back.\n  user.transform(transformEnemyId);\n  // Clear the archived data.\n  user._prevEnemyId = undefined;\n}\n</Custom Remove Effect>","overlay":0,"priority":50,"removeAtBattleEnd":false,"removeByDamage":false,"removeByRestriction":false,"removeByWalking":false,"restriction":0,"stepsToRemove":100},
{"id":120,"autoRemovalTiming":0,"chanceByDamage":100,"traits":[],"iconIndex":17,"maxTurns":1,"message1":"","message2":"","message3":"","message4":"","minTurns":1,"motion":0,"name":"Flan - Transform 2","note":"<Custom Passive Condition>\nif (!user.isStateAffected(40) && user.hp / user.mhp < 0.3) {\n    condition = true;\nif (user.isEnemy()) {\n  // Archive the previous enemy ID.\n  user._prevEnemyId = user._enemyId;\n  // Set the target enemy ID you want the enemy to change into.\n  var transformEnemyId = 56;\n  // Transform the user.\n  user.transform(transformEnemyId);\n}\n  } else {\n    condition = false;\n}\n</Custom Passive Condition>","overlay":0,"priority":50,"removeAtBattleEnd":false,"removeByDamage":false,"removeByRestriction":false,"removeByWalking":false,"restriction":0,"stepsToRemove":100},
{"id":121,"autoRemovalTiming":0,"chanceByDamage":100,"traits":[],"iconIndex":0,"maxTurns":1,"message1":"","message2":"","message3":"","message4":"","minTurns":1,"motion":0,"name":"Flare-Break","note":"","overlay":0,"priority":50,"removeAtBattleEnd":false,"removeByDamage":false,"removeByRestriction":false,"removeByWalking":false,"restriction":0,"stepsToRemove":100},
{"id":122,"autoRemovalTiming":0,"chanceByDamage":100,"traits":[],"iconIndex":0,"maxTurns":1,"message1":"","message2":"","message3":"","message4":"","minTurns":1,"motion":0,"name":"Koishi-LittleRock","note":"<Cannot Select: SType 29>\n<Cannot Select: SType 3>\n<Cannot Select: SType 12>\n<Cannot Select: SType 14>\n<Cannot Select: Skill 82>\n\n<Custom Passive Condition>\nif (!user.isStateAffected(40)) {\n    condition = true;\n  } else {\n    condition = false;\n  }\n</Custom Passive Condition>","overlay":0,"priority":50,"removeAtBattleEnd":false,"removeByDamage":false,"removeByRestriction":false,"removeByWalking":false,"restriction":0,"stepsToRemove":100},
{"id":123,"autoRemovalTiming":0,"chanceByDamage":100,"traits":[{"code":32,"dataId":108,"value":1}],"iconIndex":0,"maxTurns":1,"message1":"","message2":"","message3":"","message4":"","minTurns":1,"motion":0,"name":"MarisSatori","note":"","overlay":0,"priority":50,"removeAtBattleEnd":false,"removeByDamage":false,"removeByRestriction":false,"removeByWalking":false,"restriction":0,"stepsToRemove":100},
{"id":124,"autoRemovalTiming":0,"chanceByDamage":100,"traits":[{"code":44,"dataId":295,"value":1},{"code":44,"dataId":296,"value":1},{"code":44,"dataId":297,"value":1},{"code":44,"dataId":292,"value":1},{"code":44,"dataId":294,"value":1},{"code":44,"dataId":291,"value":1}],"iconIndex":0,"maxTurns":1,"message1":"","message2":"","message3":"","message4":"","minTurns":1,"motion":0,"name":"Yukari State 1","note":"","overlay":0,"priority":50,"removeAtBattleEnd":false,"removeByDamage":false,"removeByRestriction":false,"removeByWalking":false,"restriction":0,"stepsToRemove":100},
{"id":125,"autoRemovalTiming":0,"chanceByDamage":100,"traits":[{"code":44,"dataId":295,"value":1},{"code":44,"dataId":296,"value":1},{"code":44,"dataId":297,"value":1},{"code":44,"dataId":292,"value":1},{"code":44,"dataId":293,"value":1},{"code":44,"dataId":291,"value":1}],"iconIndex":0,"maxTurns":1,"message1":"","message2":"","message3":"","message4":"","minTurns":1,"motion":0,"name":"Yukari State 2","note":"","overlay":0,"priority":50,"removeAtBattleEnd":false,"removeByDamage":false,"removeByRestriction":false,"removeByWalking":false,"restriction":0,"stepsToRemove":100},
{"id":126,"autoRemovalTiming":0,"chanceByDamage":100,"traits":[{"code":44,"dataId":296,"value":1},{"code":44,"dataId":297,"value":1},{"code":44,"dataId":292,"value":1},{"code":44,"dataId":293,"value":1},{"code":44,"dataId":294,"value":1},{"code":44,"dataId":291,"value":1}],"iconIndex":0,"maxTurns":1,"message1":"","message2":"","message3":"","message4":"","minTurns":1,"motion":0,"name":"Yukari State 3","note":"","overlay":0,"priority":50,"removeAtBattleEnd":false,"removeByDamage":false,"removeByRestriction":false,"removeByWalking":false,"restriction":0,"stepsToRemove":100},
{"id":127,"autoRemovalTiming":0,"chanceByDamage":100,"traits":[{"code":44,"dataId":295,"value":1},{"code":44,"dataId":296,"value":1},{"code":44,"dataId":292,"value":1},{"code":44,"dataId":293,"value":1},{"code":44,"dataId":294,"value":1},{"code":44,"dataId":291,"value":1}],"iconIndex":0,"maxTurns":1,"message1":"","message2":"","message3":"","message4":"","minTurns":1,"motion":0,"name":"Yukari State 4","note":"","overlay":0,"priority":50,"removeAtBattleEnd":false,"removeByDamage":false,"removeByRestriction":false,"removeByWalking":false,"restriction":0,"stepsToRemove":100},
{"id":128,"autoRemovalTiming":0,"chanceByDamage":100,"traits":[{"code":44,"dataId":295,"value":1},{"code":44,"dataId":297,"value":1},{"code":44,"dataId":292,"value":1},{"code":44,"dataId":293,"value":1},{"code":44,"dataId":294,"value":1},{"code":44,"dataId":291,"value":1}],"iconIndex":0,"maxTurns":1,"message1":"","message2":"","message3":"","message4":"","minTurns":1,"motion":0,"name":"Yukari State 5","note":"","overlay":0,"priority":50,"removeAtBattleEnd":false,"removeByDamage":false,"removeByRestriction":false,"removeByWalking":false,"restriction":0,"stepsToRemove":100},
{"id":129,"autoRemovalTiming":0,"chanceByDamage":100,"traits":[{"code":44,"dataId":295,"value":1},{"code":44,"dataId":296,"value":1},{"code":44,"dataId":297,"value":1},{"code":44,"dataId":293,"value":1},{"code":44,"dataId":294,"value":1},{"code":44,"dataId":291,"value":1}],"iconIndex":0,"maxTurns":1,"message1":"","message2":"","message3":"","message4":"","minTurns":1,"motion":0,"name":"Yukari State 6","note":"","overlay":0,"priority":50,"removeAtBattleEnd":false,"removeByDamage":false,"removeByRestriction":false,"removeByWalking":false,"restriction":0,"stepsToRemove":100},
{"id":130,"autoRemovalTiming":0,"chanceByDamage":100,"traits":[],"iconIndex":0,"maxTurns":1,"message1":"","message2":"","message3":"","message4":"","minTurns":1,"motion":0,"name":"Envy","note":"","overlay":0,"priority":50,"removeAtBattleEnd":false,"removeByDamage":false,"removeByRestriction":false,"removeByWalking":false,"restriction":0,"stepsToRemove":100},
{"id":131,"autoRemovalTiming":0,"chanceByDamage":100,"traits":[],"iconIndex":0,"maxTurns":1,"message1":"","message2":"","message3":"","message4":"","minTurns":1,"motion":0,"name":"Spirited","note":"","overlay":0,"priority":50,"removeAtBattleEnd":false,"removeByDamage":true,"removeByRestriction":false,"removeByWalking":false,"restriction":0,"stepsToRemove":100},
{"id":132,"autoRemovalTiming":0,"chanceByDamage":100,"traits":[{"code":44,"dataId":295,"value":1},{"code":44,"dataId":296,"value":1},{"code":44,"dataId":297,"value":1},{"code":44,"dataId":292,"value":1},{"code":44,"dataId":294,"value":1},{"code":44,"dataId":293,"value":1}],"iconIndex":0,"maxTurns":1,"message1":"","message2":"","message3":"","message4":"","minTurns":1,"motion":0,"name":"Yukari State 7","note":"","overlay":0,"priority":50,"removeAtBattleEnd":false,"removeByDamage":false,"removeByRestriction":false,"removeByWalking":false,"restriction":0,"stepsToRemove":100},
{"id":133,"autoRemovalTiming":0,"chanceByDamage":100,"traits":[{"code":44,"dataId":275,"value":1},{"code":43,"dataId":33,"value":1}],"iconIndex":0,"maxTurns":1,"message1":"","message2":"","message3":"","message4":"","minTurns":1,"motion":0,"name":"GrimoireH","note":"<Custom Passive Condition>\nif (!user.isStateAffected(40)) {\n    condition = true;\n  } else {\n    condition = false;\n  }\n</Custom Passive Condition>","overlay":0,"priority":50,"removeAtBattleEnd":false,"removeByDamage":false,"removeByRestriction":false,"removeByWalking":false,"restriction":0,"stepsToRemove":100},
{"id":134,"autoRemovalTiming":1,"chanceByDamage":100,"traits":[{"code":21,"dataId":3,"value":10},{"code":21,"dataId":5,"value":0},{"code":44,"dataId":302,"value":1}],"iconIndex":0,"maxTurns":2,"message1":"","message2":"","message3":"","message4":"","minTurns":2,"motion":0,"name":"FF","note":"","overlay":0,"priority":50,"removeAtBattleEnd":true,"removeByDamage":false,"removeByRestriction":false,"removeByWalking":false,"restriction":0,"stepsToRemove":100},
{"id":135,"autoRemovalTiming":1,"chanceByDamage":100,"traits":[{"code":22,"dataId":5,"value":10},{"code":44,"dataId":303,"value":1}],"iconIndex":0,"maxTurns":3,"message1":"","message2":"","message3":"","message4":"","minTurns":3,"motion":0,"name":"AC","note":"","overlay":0,"priority":50,"removeAtBattleEnd":true,"removeByDamage":false,"removeByRestriction":false,"removeByWalking":false,"restriction":0,"stepsToRemove":100},
{"id":136,"autoRemovalTiming":0,"chanceByDamage":100,"traits":[],"iconIndex":75,"maxTurns":1,"message1":"","message2":"","message3":"","message4":"","minTurns":1,"motion":0,"name":"AutoLife","note":"<Category: Bypass Death Removal>\n\n<Custom Deselect Effect>\n// Check if the target's HP is 0 or is currently in the death state.\nif (target.hp <= 0 || target.isDead()) {\n  // Play the auto-life animation on target.\n  target.startAnimation(49);\n  // Set the amount of HP recovered to 10%.\n  var rate = 0.40;\n  // Calculate the HP healed.\n  var heal = Math.floor(target.mhp * rate);\n  // Remove the Auto-Life state.\n  target.removeState(stateId);\n  // Heal the target.\n  target.gainHp(heal);\n  // Make the damage popup show for the heal.\n  target.startDamagePopup();\n  // Clear the target's results.\n  target.clearResult();\n}\n</Custom Deselect Effect>","overlay":0,"priority":50,"removeAtBattleEnd":true,"removeByDamage":false,"removeByRestriction":false,"removeByWalking":false,"restriction":0,"stepsToRemove":100},
{"id":137,"autoRemovalTiming":0,"chanceByDamage":100,"traits":[{"code":44,"dataId":291,"value":1}],"iconIndex":0,"maxTurns":1,"message1":"","message2":"","message3":"","message4":"","minTurns":1,"motion":0,"name":"SpiritedYukari","note":"","overlay":0,"priority":50,"removeAtBattleEnd":false,"removeByDamage":false,"removeByRestriction":false,"removeByWalking":false,"restriction":0,"stepsToRemove":100},
{"id":138,"autoRemovalTiming":1,"chanceByDamage":20,"traits":[{"code":22,"dataId":5,"value":1},{"code":44,"dataId":283,"value":1}],"iconIndex":164,"maxTurns":3,"message1":"","message2":"","message3":"","message4":"","minTurns":3,"motion":0,"name":"Catadioptric","note":"","overlay":0,"priority":50,"removeAtBattleEnd":false,"removeByDamage":true,"removeByRestriction":false,"removeByWalking":false,"restriction":0,"stepsToRemove":100},
{"id":139,"autoRemovalTiming":0,"chanceByDamage":100,"traits":[],"iconIndex":0,"maxTurns":1,"message1":"","message2":"","message3":"","message4":"","minTurns":1,"motion":0,"name":"","note":"","overlay":0,"priority":50,"removeAtBattleEnd":false,"removeByDamage":false,"removeByRestriction":false,"removeByWalking":false,"restriction":0,"stepsToRemove":100},
{"id":140,"autoRemovalTiming":0,"chanceByDamage":100,"traits":[],"iconIndex":0,"maxTurns":1,"message1":"","message2":"","message3":"","message4":"","minTurns":1,"motion":0,"name":"","note":"","overlay":0,"priority":50,"removeAtBattleEnd":false,"removeByDamage":false,"removeByRestriction":false,"removeByWalking":false,"restriction":0,"stepsToRemove":100},
{"id":141,"autoRemovalTiming":0,"chanceByDamage":100,"traits":[],"iconIndex":0,"maxTurns":1,"message1":"","message2":"","message3":"","message4":"","minTurns":1,"motion":0,"name":"","note":"","overlay":0,"priority":50,"removeAtBattleEnd":false,"removeByDamage":false,"removeByRestriction":false,"removeByWalking":false,"restriction":0,"stepsToRemove":100},
{"id":142,"autoRemovalTiming":0,"chanceByDamage":100,"traits":[],"iconIndex":0,"maxTurns":1,"message1":"","message2":"","message3":"","message4":"","minTurns":1,"motion":0,"name":"","note":"","overlay":0,"priority":50,"removeAtBattleEnd":false,"removeByDamage":false,"removeByRestriction":false,"removeByWalking":false,"restriction":0,"stepsToRemove":100},
{"id":143,"autoRemovalTiming":0,"chanceByDamage":100,"traits":[],"iconIndex":0,"maxTurns":1,"message1":"","message2":"","message3":"","message4":"","minTurns":1,"motion":0,"name":"","note":"","overlay":0,"priority":50,"removeAtBattleEnd":false,"removeByDamage":false,"removeByRestriction":false,"removeByWalking":false,"restriction":0,"stepsToRemove":100},
{"id":144,"autoRemovalTiming":0,"chanceByDamage":100,"traits":[],"iconIndex":0,"maxTurns":1,"message1":"","message2":"","message3":"","message4":"","minTurns":1,"motion":0,"name":"","note":"","overlay":0,"priority":50,"removeAtBattleEnd":false,"removeByDamage":false,"removeByRestriction":false,"removeByWalking":false,"restriction":0,"stepsToRemove":100},
{"id":145,"autoRemovalTiming":0,"chanceByDamage":100,"traits":[],"iconIndex":0,"maxTurns":1,"message1":"","message2":"","message3":"","message4":"","minTurns":1,"motion":0,"name":"","note":"","overlay":0,"priority":50,"removeAtBattleEnd":false,"removeByDamage":false,"removeByRestriction":false,"removeByWalking":false,"restriction":0,"stepsToRemove":100}
]